MANIFEST.in
README.rst
setup.py
collective/__init__.py
collective.pygal.plonestats.egg-info/PKG-INFO
collective.pygal.plonestats.egg-info/SOURCES.txt
collective.pygal.plonestats.egg-info/dependency_links.txt
collective.pygal.plonestats.egg-info/entry_points.txt
collective.pygal.plonestats.egg-info/namespace_packages.txt
collective.pygal.plonestats.egg-info/not-zip-safe
collective.pygal.plonestats.egg-info/requires.txt
collective.pygal.plonestats.egg-info/top_level.txt
collective/pygal/__init__.py
collective/pygal/plonestats/__init__.py
collective/pygal/plonestats/configure.zcml
collective/pygal/plonestats/tests.py
collective/pygal/plonestats/version.txt
collective/pygal/plonestats/browser/__init__.py
collective/pygal/plonestats/browser/configure.zcml
collective/pygal/plonestats/browser/plonestats.pt
collective/pygal/plonestats/browser/views.py
docs/HISTORY.txt
docs/INSTALL.txt
docs/LICENSE.txt