Metadata-Version: 1.0
Name: collective.pygal.plonestats
Version: 0.1
Summary: Simple plone portalindex statistics with pygal
Home-page: https://github.com/collective/collective.pygal.plonestats
Author: Christian Ledermann
Author-email: christian.ledermann@gmail.com
License: GPL
Platform: UNKNOWN
Classifier: Framework :: Plone
Classifier: Framework :: Plone :: 4.0
Classifier: Framework :: Plone :: 4.1
Classifier: Environment :: Web Environment
Classifier: License :: OSI Approved :: GNU General Public License (GPL)
Classifier: Programming Language :: Python :: 2
Classifier: Topic :: Multimedia :: Graphics :: Presentation
